LICENSE.txt
README.rst
pyproject.toml
ebm2onnx/__init__.py
ebm2onnx/context.py
ebm2onnx/convert.py
ebm2onnx/ebm.py
ebm2onnx/graph.py
ebm2onnx/operators.py
ebm2onnx/operators_ml.py
ebm2onnx/sklearn.py
ebm2onnx/utils.py
ebm2onnx.egg-info/PKG-INFO
ebm2onnx.egg-info/SOURCES.txt
ebm2onnx.egg-info/dependency_links.txt
ebm2onnx.egg-info/requires.txt
ebm2onnx.egg-info/top_level.txt
tests/test_convert.py
tests/test_ebm.py
tests/test_graph.py
tests/test_operators.py
tests/test_operators_ml.py
tests/test_pandas_dtype.py
tests/test_sklearn.py