Metadata-Version: 2.4
Name: ebm2onnx
Version: 3.3.1
Summary: EBM model serialization to ONNX
Author: Romain Picard
Author-email: romain.picard@softathome.com
License: MIT License
Project-URL: repository, https://github.com/interpretml/ebm2onnx.git
Keywords: ebm2onnx,interpretml,machine-learning,onnx
Classifier: Development Status :: 4 - Beta
Classifier: Intended Audience :: Developers
Classifier: License :: OSI Approved :: MIT License
Classifier: Topic :: Scientific/Engineering :: Artificial Intelligence
Classifier: Natural Language :: English
Classifier: Programming Language :: Python :: 3
Requires-Python: >=3.6
License-File: LICENSE.txt
Requires-Dist: onnx~=1.8
Requires-Dist: interpret-core~=0.6
Provides-Extra: test
Requires-Dist: pytest; extra == "test"
Dynamic: license-file
